blalacar
