Metadata-Version: 2.1
Name: blalacar
Version: 1.5
Summary: blalacar
Home-page: https://github.com/EPkravec/blalacar1
Author: k.e.p
Author-email: k.e.p@gmail.com
License: UNKNOWN
Download-URL: https://github.com/EPkravec/blalacar1/archive/1.5.tar.gz
Keywords: blalacar1
Platform: UNKNOWN
